fischer_mdls/__init__.py
fischer_mdls/mdls.py
fischer_mdls/utils.py
fischer-0.1.3.dist-info/METADATA
fischer-0.1.3.dist-info/WHEEL
fischer-0.1.3.dist-info/top_level.txt
fischer-0.1.3.dist-info/RECORD
