Metadata-Version: 2.1
Name: fischer
Version: 0.1.3
Home-page: https://github.com/Fischer-pixel/MDLS
Author: Fischer-pixel
License: MIT Licence
Platform: any
Requires-Python: >=3.6.0
Requires-Dist: numpy
Requires-Dist: scikit-learn
Requires-Dist: PyMieScatt
Requires-Dist: tqdm
Requires-Dist: scipy
